MANIFEST.in
README.md
requirements.txt
setup.cfg
setup.py
domba/__init__.py
domba/cli.py
domba/clis/__init__.py
domba/clis/base.py
domba/clis/command.py
domba/clis/envi.py
domba/clis/start.py
domba/clis/zone.py
domba/libs/__init__.py
domba/libs/command_lib.py
domba/libs/env_lib.py
domba/libs/kafka_lib.py
domba/libs/knot_lib.py
domba/libs/utils.py
domba/libs/libcommand/__init__.py
domba/libs/libcommand/control/__init__.py
domba/libs/libcommand/control/client.py
domba/libs/libcommand/control/libknot/__init__.py
domba/libs/libcommand/control/libknot/control.py
domba/libs/libcommand/parse/__init__.py
domba/libs/libcommand/parse/parser.py
domba/libs/libcommand/utility/__init__.py
domba/libs/libcommand/utility/utils.py
test/test_vm.py