Metadata-Version: 2.1
Name: domba
Version: 0.7.3
Summary: Agent For RESTKnot
Home-page: https://github.com/meongbego/domba
Author: iank
Author-email: meongbego@gmail.com
License: MIT
Keywords: knot agent rest restknot
Platform: UNKNOWN
Classifier: Intended Audience :: Developers
Classifier: Topic :: Utilities
Classifier: License :: Public Domain
Classifier: Natural Language :: English
Classifier: Operating System :: OS Independent
Classifier: Programming Language :: Python :: 3
Classifier: Programming Language :: Python :: 3.2
Classifier: Programming Language :: Python :: 3.3
Classifier: Programming Language :: Python :: 3.4
Classifier: Programming Language :: Python :: 3.5
Classifier: Programming Language :: Python :: 3.6
Classifier: Programming Language :: Python :: 3.7
Provides-Extra: test
